napari_tiledb_bioimg/__init__.py
napari_tiledb_bioimg/_reader.py
napari_tiledb_bioimg/_version.py
napari_tiledb_bioimg/_widget.py
napari_tiledb_bioimg/_writer.py
napari_tiledb_bioimg/napari.yaml
napari_tiledb_bioimg/samples/CMU-1-Small-Region.tdb/__tiledb_group.tdb
napari_tiledb_bioimg/samples/CMU-1-Small-Region.tdb/__group/__1683859166939_1683859166939_90e51ed0f4064708b30f942749302bd2_2
napari_tiledb_bioimg/samples/CMU-1-Small-Region.tdb/__meta/__1683859166940_1683859166940_9b63d4fe1f4e449d982481a181a8aa11
napari_tiledb_bioimg/samples/CMU-1-Small-Region.tdb/l_0.tdb/__commits/__1683859166839_1683859166839_0a866085dabc456384de3f8991f30d3d_18.wrt
napari_tiledb_bioimg/samples/CMU-1-Small-Region.tdb/l_0.tdb/__fragments/__1683859166839_1683859166839_0a866085dabc456384de3f8991f30d3d_18/__fragment_metadata.tdb
napari_tiledb_bioimg/samples/CMU-1-Small-Region.tdb/l_0.tdb/__fragments/__1683859166839_1683859166839_0a866085dabc456384de3f8991f30d3d_18/a0.tdb
napari_tiledb_bioimg/samples/CMU-1-Small-Region.tdb/l_0.tdb/__meta/__1683859166801_1683859166801_b719067bf3a54f7cbb2e1c74fa8a3aa9
napari_tiledb_bioimg/samples/CMU-1-Small-Region.tdb/l_0.tdb/__schema/__1683859166800_1683859166800_b998002fcd5c4dcb8b6308fbd78136ea
napari_tiledb_bioimg-0.0.1.dist-info/LICENSE
napari_tiledb_bioimg-0.0.1.dist-info/METADATA
napari_tiledb_bioimg-0.0.1.dist-info/WHEEL
napari_tiledb_bioimg-0.0.1.dist-info/entry_points.txt
napari_tiledb_bioimg-0.0.1.dist-info/top_level.txt
napari_tiledb_bioimg-0.0.1.dist-info/RECORD
