Metadata-Version: 2.1
Name: napari-tiledb-bioimg
Version: 0.0.1
Summary: Support reading and writing TileDB-Bioimaging image arrays within Napari
Home-page: https://github.com/TileDB-Inc/napari-tiledb-bioimg
Author: TileDB, Inc.
Author-email: help@tiledb.io
License: MIT
Classifier: Development Status :: 2 - Pre-Alpha
Classifier: Framework :: napari
Classifier: Intended Audience :: Developers
Classifier: License :: OSI Approved :: MIT License
Classifier: Operating System :: OS Independent
Classifier: Programming Language :: Python
Classifier: Programming Language :: Python :: 3
Classifier: Programming Language :: Python :: 3 :: Only
Classifier: Programming Language :: Python :: 3.8
Classifier: Programming Language :: Python :: 3.9
Classifier: Programming Language :: Python :: 3.10
Classifier: Topic :: Scientific/Engineering :: Image Processing
Requires-Python: >=3.8
License-File: LICENSE
Requires-Dist: dask
Requires-Dist: tiledb-bioimg (>=0.2.1)
Provides-Extra: cloud
Requires-Dist: tiledb-cloud ; extra == 'cloud'
Provides-Extra: testing
Requires-Dist: napari ; extra == 'testing'
Requires-Dist: tox ; extra == 'testing'
Requires-Dist: pytest ; extra == 'testing'
Requires-Dist: pytest-cov ; extra == 'testing'
